{
	"info": {
		"_postman_id": "3a6a3424-e125-4467-a04b-c612ed715d97",
		"name": "E-commerce API",
		"description": "Complete API testing collection for NestJS E-commerce API",
		"schema": "https://schema.getpostman.com/json/collection/v2.1.0/collection.json",
		"_exporter_id": "145234"
	},
	"item": [
		{
			"name": "Authentication",
			"item": [
				{
					"name": "Login User",
					"event": [
						{
							"listen": "test",
							"script": {
								"exec": [
									"if (pm.response.code === 200) {",
									"    const response = pm.response.json();",
									"    pm.environment.set('token', response.access_token);",
									"    pm.test('Login successful', function () {",
									"        pm.expect(response.message).to.include('successful');",
									"        pm.expect(response.access_token).to.exist;",
									"    });",
									"}"
								],
								"type": "text/javascript"
							}
						}
					],
					"request": {
						"method": "POST",
						"header": [
							{
								"key": "Content-Type",
								"value": "application/json"
							}
						],
						"body": {
							"mode": "raw",
							"raw": "{\n  \"username\": \"demo\",\n  \"password\": \"password123\"\n}"
						},
						"url": {
							"raw": "{{base_url}}/auth/login",
							"host": [
								"{{base_url}}"
							],
							"path": [
								"auth",
								"login"
							]
						}
					},
					"response": []
				}
			]
		},
		{
			"name": "Categories",
			"item": [
				{
					"name": "Get All Categories",
					"event": [
						{
							"listen": "test",
							"script": {
								"exec": [
									"pm.test('Status code is 200', function () {",
									"    pm.response.to.have.status(200);",
									"});",
									"",
									"pm.test('Categories array exists', function () {",
									"    const response = pm.response.json();",
									"    pm.expect(response).to.be.an('array');",
									"});",
									"",
									"if (pm.response.json().length > 0) {",
									"    pm.environment.set('categoryId', pm.response.json()[0].id);",
									"}"
								],
								"type": "text/javascript"
							}
						}
					],
					"request": {
						"method": "GET",
						"header": [],
						"url": {
							"raw": "{{base_url}}/categories",
							"host": [
								"{{base_url}}"
							],
							"path": [
								"categories"
							]
						}
					},
					"response": []
				},
				{
					"name": "Get Category by ID",
					"request": {
						"method": "GET",
						"header": [],
						"url": {
							"raw": "{{base_url}}/categories/1",
							"host": [
								"{{base_url}}"
							],
							"path": [
								"categories",
								"1"
							]
						}
					},
					"response": []
				},
				{
					"name": "Create Category",
					"request": {
						"auth": {
							"type": "bearer",
							"bearer": [
								{
									"key": "token",
									"value": "{{token}}",
									"type": "string"
								}
							]
						},
						"method": "POST",
						"header": [
							{
								"key": "Content-Type",
								"value": "application/json"
							}
						],
						"body": {
							"mode": "raw",
							"raw": "{\n  \"name\": \"Test Category\",\n  \"description\": \"A test category for API testing\"\n}"
						},
						"url": {
							"raw": "{{base_url}}/categories",
							"host": [
								"{{base_url}}"
							],
							"path": [
								"categories"
							]
						}
					},
					"response": []
				}
			]
		},
		{
			"name": "Products",
			"item": [
				{
					"name": "Get All Products",
					"event": [
						{
							"listen": "test",
							"script": {
								"exec": [
									"pm.test('Status code is 200', function () {",
									"    pm.response.to.have.status(200);",
									"});",
									"",
									"pm.test('Response has pagination structure', function () {",
									"    const response = pm.response.json();",
									"    pm.expect(response).to.have.property('data');",
									"    pm.expect(response).to.have.property('total');",
									"    pm.expect(response).to.have.property('page');",
									"});",
									"",
									"if (pm.response.json().data.length > 0) {",
									"    pm.environment.set('productId', pm.response.json().data[0].id);",
									"}"
								],
								"type": "text/javascript"
							}
						}
					],
					"request": {
						"method": "GET",
						"header": [],
						"url": {
							"raw": "{{base_url}}/products?page=1&limit=10",
							"host": [
								"{{base_url}}"
							],
							"path": [
								"products"
							],
							"query": [
								{
									"key": "page",
									"value": "1"
								},
								{
									"key": "limit",
									"value": "10"
								}
							]
						}
					},
					"response": []
				},
				{
					"name": "Get Products by Category",
					"request": {
						"method": "GET",
						"header": [],
						"url": {
							"raw": "{{base_url}}/products?categoryId={{categoryId}}",
							"host": [
								"{{base_url}}"
							],
							"path": [
								"products"
							],
							"query": [
								{
									"key": "categoryId",
									"value": "{{categoryId}}"
								}
							]
						}
					},
					"response": []
				},
				{
					"name": "Get Product by ID",
					"request": {
						"method": "GET",
						"header": [],
						"url": {
							"raw": "{{base_url}}/products/{{productId}}",
							"host": [
								"{{base_url}}"
							],
							"path": [
								"products",
								"{{productId}}"
							]
						}
					},
					"response": []
				},
				{
					"name": "Create Product",
					"request": {
						"auth": {
							"type": "bearer",
							"bearer": [
								{
									"key": "token",
									"value": "{{token}}",
									"type": "string"
								}
							]
						},
						"method": "POST",
						"header": [
							{
								"key": "Content-Type",
								"value": "application/json"
							}
						],
						"body": {
							"mode": "raw",
							"raw": "{\n  \"name\": \"Test Product\",\n  \"description\": \"A test product for API testing\",\n  \"price\": 99.99,\n  \"stock\": 50,\n  \"categoryId\": 1\n}"
						},
						"url": {
							"raw": "{{base_url}}/products",
							"host": [
								"{{base_url}}"
							],
							"path": [
								"products"
							]
						}
					},
					"response": []
				}
			]
		},
		{
			"name": "Shopping Cart",
			"item": [
				{
					"name": "Get Cart",
					"event": [
						{
							"listen": "test",
							"script": {
								"exec": [
									"pm.test('Status code is 200', function () {",
									"    pm.response.to.have.status(200);",
									"});",
									"",
									"pm.test('Cart structure is correct', function () {",
									"    const response = pm.response.json();",
									"    pm.expect(response).to.have.property('items');",
									"    pm.expect(response).to.have.property('summary');",
									"});"
								],
								"type": "text/javascript"
							}
						}
					],
					"request": {
						"auth": {
							"type": "bearer",
							"bearer": [
								{
									"key": "token",
									"value": "{{token}}",
									"type": "string"
								}
							]
						},
						"method": "GET",
						"header": [],
						"url": {
							"raw": "{{base_url}}/cart",
							"host": [
								"{{base_url}}"
							],
							"path": [
								"cart"
							]
						}
					},
					"response": []
				},
				{
					"name": "Add Product to Cart",
					"event": [
						{
							"listen": "test",
							"script": {
								"exec": [
									"pm.test('Product added to cart', function () {",
									"    pm.response.to.have.status(201);",
									"    const response = pm.response.json();",
									"    pm.expect(response.message).to.include('added to cart');",
									"});"
								],
								"type": "text/javascript"
							}
						}
					],
					"request": {
						"auth": {
							"type": "bearer",
							"bearer": [
								{
									"key": "token",
									"value": "{{token}}",
									"type": "string"
								}
							]
						},
						"method": "POST",
						"header": [
							{
								"key": "Content-Type",
								"value": "application/json"
							}
						],
						"body": {
							"mode": "raw",
							"raw": "{\n  \"productId\": {{productId}},\n  \"quantity\": 2\n}"
						},
						"url": {
							"raw": "{{base_url}}/cart",
							"host": [
								"{{base_url}}"
							],
							"path": [
								"cart"
							]
						}
					},
					"response": []
				},
				{
					"name": "Update Cart Item Quantity",
					"request": {
						"auth": {
							"type": "bearer",
							"bearer": [
								{
									"key": "token",
									"value": "{{token}}",
									"type": "string"
								}
							]
						},
						"method": "PUT",
						"header": [
							{
								"key": "Content-Type",
								"value": "application/json"
							}
						],
						"body": {
							"mode": "raw",
							"raw": "{\n  \"quantity\": 3\n}"
						},
						"url": {
							"raw": "{{base_url}}/cart/{{productId}}",
							"host": [
								"{{base_url}}"
							],
							"path": [
								"cart",
								"{{productId}}"
							]
						}
					},
					"response": []
				},
				{
					"name": "Remove Product from Cart",
					"request": {
						"auth": {
							"type": "bearer",
							"bearer": [
								{
									"key": "token",
									"value": "{{token}}",
									"type": "string"
								}
							]
						},
						"method": "DELETE",
						"header": [],
						"url": {
							"raw": "{{base_url}}/cart/{{productId}}",
							"host": [
								"{{base_url}}"
							],
							"path": [
								"cart",
								"{{productId}}"
							]
						}
					},
					"response": []
				},
				{
					"name": "Clear Cart",
					"request": {
						"auth": {
							"type": "bearer",
							"bearer": [
								{
									"key": "token",
									"value": "{{token}}",
									"type": "string"
								}
							]
						},
						"method": "DELETE",
						"header": [],
						"url": {
							"raw": "{{base_url}}/cart",
							"host": [
								"{{base_url}}"
							],
							"path": [
								"cart"
							]
						}
					},
					"response": []
				}
			]
		}
	],
	"auth": {
		"type": "bearer",
		"bearer": [
			{
				"key": "token",
				"value": "{{token}}",
				"type": "string"
			}
		]
	},
	"event": [
		{
			"listen": "prerequest",
			"script": {
				"type": "text/javascript",
				"exec": [
					""
				]
			}
		},
		{
			"listen": "test",
			"script": {
				"type": "text/javascript",
				"exec": [
					""
				]
			}
		}
	],
	"variable": [
		{
			"key": "base_url",
			"value": "http://localhost:3000"
		},
		{
			"key": "token",
			"value": ""
		}
	]
}